zip3/__init__.py
zip3/zip3.py
zip3-1.0.2.dist-info/LICENSE
zip3-1.0.2.dist-info/METADATA
zip3-1.0.2.dist-info/WHEEL
zip3-1.0.2.dist-info/top_level.txt
zip3-1.0.2.dist-info/RECORD
