Metadata-Version: 2.1
Name: zip3
Version: 1.0.2
Summary: A package to create a ZIP archive of all your files on S3
Home-page: https://github.com/marcotroisi/zip3
Author: Marco Troisi
Author-email: hello@marcotroisi.com
License: MIT
Platform: UNKNOWN
Classifier: License :: OSI Approved :: MIT License
Classifier: Programming Language :: Python :: 3
Classifier: Programming Language :: Python :: 3.7
Requires-Dist: boto3
